README.md
setup.py
lessweb-stubs/__init__.pyi
lessweb-stubs/application.pyi
lessweb-stubs/bridge.pyi
lessweb-stubs/context.pyi
lessweb-stubs/garage.pyi
lessweb-stubs/model.pyi
lessweb-stubs/storage.pyi
lessweb-stubs/typehint.pyi
lessweb-stubs/utils.pyi
lessweb-stubs/webapi.pyi
lessweb-stubs/plugin/__init__.pyi
lessweb-stubs/plugin/database.pyi
lessweb-stubs/plugin/dome.pyi
lessweb-stubs/plugin/redis.pyi
lessweb-stubs/plugin/weixin.pyi
lessweb_stubs.egg-info/PKG-INFO
lessweb_stubs.egg-info/SOURCES.txt
lessweb_stubs.egg-info/dependency_links.txt
lessweb_stubs.egg-info/requires.txt
lessweb_stubs.egg-info/top_level.txt