Metadata-Version: 1.0
Name: lessweb-stubs
Version: 0.1
Summary: lessweb stubs「嘞是web」
Home-page: https://github.com/qorzj/lessweb
Author: qorzj
Author-email: inull@qq.com
License: MIT License
Keywords: lessweb web web.py stubs
Platform: UNKNOWN
